alibabacloud_iacservice20210806/__init__.py
alibabacloud_iacservice20210806/client.py
alibabacloud_iacservice20210806/models/__init__.py
alibabacloud_iacservice20210806/models/_add_shared_accounts_request.py
alibabacloud_iacservice20210806/models/_add_shared_accounts_response.py
alibabacloud_iacservice20210806/models/_add_shared_accounts_response_body.py
alibabacloud_iacservice20210806/models/_associate_group_request.py
alibabacloud_iacservice20210806/models/_associate_group_response.py
alibabacloud_iacservice20210806/models/_associate_group_response_body.py
alibabacloud_iacservice20210806/models/_cancel_resource_export_task_request.py
alibabacloud_iacservice20210806/models/_cancel_resource_export_task_response.py
alibabacloud_iacservice20210806/models/_cancel_resource_export_task_response_body.py
alibabacloud_iacservice20210806/models/_create_group_request.py
alibabacloud_iacservice20210806/models/_create_group_response.py
alibabacloud_iacservice20210806/models/_create_group_response_body.py
alibabacloud_iacservice20210806/models/_create_job_request.py
alibabacloud_iacservice20210806/models/_create_job_response.py
alibabacloud_iacservice20210806/models/_create_job_response_body.py
alibabacloud_iacservice20210806/models/_create_module_request.py
alibabacloud_iacservice20210806/models/_create_module_response.py
alibabacloud_iacservice20210806/models/_create_module_response_body.py
alibabacloud_iacservice20210806/models/_create_module_version_request.py
alibabacloud_iacservice20210806/models/_create_module_version_response.py
alibabacloud_iacservice20210806/models/_create_module_version_response_body.py
alibabacloud_iacservice20210806/models/_create_project_request.py
alibabacloud_iacservice20210806/models/_create_project_response.py
alibabacloud_iacservice20210806/models/_create_project_response_body.py
alibabacloud_iacservice20210806/models/_create_registry_module_request.py
alibabacloud_iacservice20210806/models/_create_registry_module_response.py
alibabacloud_iacservice20210806-2.2.0.dist-info/LICENSE
alibabacloud_iacservice20210806-2.2.0.dist-info/METADATA
alibabacloud_iacservice20210806-2.2.0.dist-info/WHEEL
alibabacloud_iacservice20210806-2.2.0.dist-info/top_level.txt
alibabacloud_iacservice20210806-2.2.0.dist-info/RECORD
